file_sort_app/__init__.py
file_sort_app/cli.py
file_sort_app/file_sort_app.py
file_sort_app/imviewer.py
file_sort_app-0.1.1.dist-info/AUTHORS.rst
file_sort_app-0.1.1.dist-info/LICENSE
file_sort_app-0.1.1.dist-info/METADATA
file_sort_app-0.1.1.dist-info/WHEEL
file_sort_app-0.1.1.dist-info/entry_points.txt
file_sort_app-0.1.1.dist-info/top_level.txt
file_sort_app-0.1.1.dist-info/RECORD
