Metadata-Version: 2.1
Name: file-sort-app
Version: 0.1.1
Summary: Interactive application to sort image files into folders.
Home-page: https://github.com/EyreC/file_sort_app
Author: Alexander Craggs
Author-email: eyrecraggs@gmail.com
License: MIT license
Keywords: file_sort_app
Platform: UNKNOWN
Classifier: Development Status :: 2 - Pre-Alpha
Classifier: Intended Audience :: Developers
Classifier: License :: OSI Approved :: MIT License
Classifier: Natural Language :: English
Classifier: Programming Language :: Python :: 2
Classifier: Programming Language :: Python :: 2.7
Classifier: Programming Language :: Python :: 3
Classifier: Programming Language :: Python :: 3.4
Classifier: Programming Language :: Python :: 3.5
Classifier: Programming Language :: Python :: 3.6
Classifier: Programming Language :: Python :: 3.7
Requires-Dist: Click (>=6.0)
